{"0_1":{"link":"1_1","offset":{"x":20,"y":120},"start_id":"Caipora"},"1_1":{"dialogue":"Tem alguma coisa nesse mato","offset":{"x":220,"y":0},"options":{"0":{"link":"1_2","text":"..."}},"size":{"x":200,"y":255.000031},"speaker":"Pedro"},"1_2":{"dialogue":"[color=red] Sem papo amigo, agora venha[/color]","offset":{"x":460,"y":0},"options":{"0":{"link":"1_3","text":"..."}},"size":{"x":200.000183,"y":255.000031},"speaker":"Caipora"},"1_3":{"dialogue":"[color=red]HIIIIIIIIIIII!!!!!!! [/color]","offset":{"x":700,"y":0},"options":{"0":{"link":"END","text":""}},"size":{"x":200,"y":255.000031},"speaker":"Javali"},"comments":{},"start":{"Caipora":"0_1"},"strays":{},"variables":{}}
